bionetcomp/__init__.py
bionetcomp/bignetwork_ppi.py
bionetcomp/bionetcomp.py
bionetcomp/comparative_matrics.py
bionetcomp/comparative_metrics.py
bionetcomp/compare_networks.py
bionetcomp/edges_by_network.py
bionetcomp/enrichment_network.py
bionetcomp/enrichment_network_old.py
bionetcomp/enrichment_small_network.py
bionetcomp/network_development.py
bionetcomp/network_enrichment.py
bionetcomp/smallnetwork_ppi.py
bionetcomp-1.1.dist-info/LICENSE
bionetcomp-1.1.dist-info/METADATA
bionetcomp-1.1.dist-info/WHEEL
bionetcomp-1.1.dist-info/entry_points.txt
bionetcomp-1.1.dist-info/top_level.txt
bionetcomp-1.1.dist-info/RECORD
