Metadata-Version: 2.1
Name: bionetcomp
Version: 1.1
Summary: BioNetComp: A Python package for biological network comparison from STRING database.
Home-page: https://github.com/lmigueel/bionetcomp/
Author: Luca Miguel de Carvalho
Author-email: lucasmigueel@gmail.com
License: GNU General Public License v3.0
Keywords: bioinformatics,PPI network,network,biological network,STRING,string
Platform: UNKNOWN
Classifier: Development Status :: 3 - Alpha
Classifier: Intended Audience :: Science/Research
Classifier: Natural Language :: English
Classifier: Topic :: Software Development :: Libraries
Classifier: Topic :: Scientific/Engineering :: Bio-Informatics
Classifier: License :: OSI Approved :: GNU General Public License (GPL)
Classifier: Programming Language :: Python :: 3
Requires-Python: >=3
Requires-Dist: matplotlib
Requires-Dist: numpy
Requires-Dist: pandas
Requires-Dist: networkx (>=2.5)
Requires-Dist: gseapy
Requires-Dist: requests
Requires-Dist: scipy (>=1.6.1)
